pulsar_cli/__init__.py
pulsar_cli/lib.py
pulsar_cli/main.py
pulsar_cli/pulsar_admin.py
pulsar_cli-0.1.0.dist-info/entry_points.txt
pulsar_cli-0.1.0.dist-info/LICENSE
pulsar_cli-0.1.0.dist-info/WHEEL
pulsar_cli-0.1.0.dist-info/METADATA
pulsar_cli-0.1.0.dist-info/RECORD
